PyBlox2/Base.py
PyBlox2/Client.py
PyBlox2/Errors.py
PyBlox2/Groups.py
PyBlox2/Member.py
PyBlox2/Ranks.py
PyBlox2/Response.py
PyBlox2/Settings.py
PyBlox2/User.py
PyBlox2/__init__.py
PyBlox2/__main__.py
PyBlox2/utils/Cache.py
PyBlox2/utils/Commands.py
PyBlox2/utils/Http.py
PyBlox2/utils/Misc.py
PyBlox2/utils/__init__.py
PyBlox2-1.0.0.dist-info/LICENSE.md
PyBlox2-1.0.0.dist-info/METADATA
PyBlox2-1.0.0.dist-info/WHEEL
PyBlox2-1.0.0.dist-info/top_level.txt
PyBlox2-1.0.0.dist-info/RECORD
