Metadata-Version: 2.1
Name: PyBlox2
Version: 1.0.0
Summary: Handler for the Roblox API
Home-page: https://github.com/Kyando2/PyBlox
Author: Kyando
Author-email: amehikoji@gmail.com
License: UNKNOWN
Platform: UNKNOWN
Classifier: Programming Language :: Python :: 3
Classifier: License :: OSI Approved :: MIT License
Classifier: Operating System :: OS Independent
Requires-Python: >=3.6
Requires-Dist: aiohttp (>=3.6.0)
